LICENSE
README.md
setup.py
mlflowcollab/__init__.py
mlflowcollab/_version.py
mlflowcollab/mlflowwrapper.py
mlflowcollab.egg-info/PKG-INFO
mlflowcollab.egg-info/SOURCES.txt
mlflowcollab.egg-info/dependency_links.txt
mlflowcollab.egg-info/requires.txt
mlflowcollab.egg-info/top_level.txt