Metadata-Version: 2.1
Name: mlflowcollab
Version: 0.0.4
Summary: Gebruik MLFlow op een centrale locatie
Home-page: https://dev.azure.com/HWH-WE-DEEP/VV-WAM/_git/mlflowcollab
Author: Sjoerd Gnodde
Author-email: sgnodde@hhdelfland.nl
License: UNKNOWN
Platform: UNKNOWN
Classifier: Programming Language :: Python :: 3
Classifier: Development Status :: 3 - Alpha
Classifier: License :: OSI Approved :: Mozilla Public License 2.0 (MPL 2.0)
Classifier: Operating System :: OS Independent
Requires-Python: >=3.6
License-File: LICENSE
